baraqdalib/__init__.py
baraqdalib/addresses.py
baraqdalib/cars.py
baraqdalib/generator.py
baraqdalib/person.py
baraqdalib/addressData/cities.csv
baraqdalib/addressData/postal_codes.csv
baraqdalib/addressData/streets.csv
baraqdalib/data/DE/age.csv
baraqdalib/data/DE/blood_type.csv
baraqdalib/data/DE/eyes.csv
baraqdalib/data/DE/female_first_name.csv
baraqdalib/data/DE/female_second_name.csv
baraqdalib/data/DE/female_surname.csv
baraqdalib/data/DE/hair.csv
baraqdalib/data/DE/male_first_name.csv
baraqdalib/data/DE/male_second_name.csv
baraqdalib/data/DE/male_surname.csv
baraqdalib/data/PL/age.csv
baraqdalib/data/PL/blood_type.csv
baraqdalib/data/PL/cars.csv
baraqdalib/data/PL/cities.csv
baraqdalib/data/PL/cities_pops.txt
baraqdalib/data/PL/eyes.csv
baraqdalib/data/PL/female_first_name.csv
baraqdalib/data/PL/female_second_name.csv
baraqdalib/data/PL/female_surname.csv
baraqdalib/data/PL/hair.csv
baraqdalib/data/PL/male_first_name.csv
baraqdalib/data/PL/male_second_name.csv
baraqdalib/data/PL/male_surname.csv
baraqdalib/data/PL/postal_codes.csv
baraqdalib/data/PL/streets.csv
baraqdalib/data/PL/cars/add_info_of_au.csv
baraqdalib/data/PL/cars/add_info_of_bmw.csv
baraqdalib/data/PL/cars/add_info_of_mb.csv
baraqdalib/data/PL/cars/add_info_of_vw.csv
tests/__init__.py
tests/addresses_test.py
tests/test.py
baraqda_lib-0.0.18.dist-info/LICENSE
baraqda_lib-0.0.18.dist-info/METADATA
baraqda_lib-0.0.18.dist-info/WHEEL
baraqda_lib-0.0.18.dist-info/top_level.txt
baraqda_lib-0.0.18.dist-info/RECORD
