Metadata-Version: 2.1
Name: baraqda-lib
Version: 0.0.18
Summary: Generator of real fake data for testing purpose using real distribution in society
Home-page: UNKNOWN
Author: Kacper Hanuszewicz, Aleksander Karbowy, Wojciech Marcinkowski, Marcin Rogoń
Author-email: baraqda-team@outlook.com
License: MIT
Platform: UNKNOWN
Classifier: Intended Audience :: Developers
Classifier: License :: OSI Approved :: MIT License
Classifier: Programming Language :: Python :: 3.8
Classifier: Programming Language :: Python :: 3.9
Classifier: Programming Language :: Python :: 3.10
Classifier: Operating System :: OS Independent
License-File: LICENSE
